napari_pymeshlab/__init__.py
napari_pymeshlab/_reader.py
napari_pymeshlab/_sample_data.py
napari_pymeshlab/_widget.py
napari_pymeshlab/_writer.py
napari_pymeshlab/napari.yaml
napari_pymeshlab/_tests/__init__.py
napari_pymeshlab/_tests/test_functions.py
napari_pymeshlab/_tests/test_reader.py
napari_pymeshlab-0.0.6.dist-info/LICENSE
napari_pymeshlab-0.0.6.dist-info/METADATA
napari_pymeshlab-0.0.6.dist-info/WHEEL
napari_pymeshlab-0.0.6.dist-info/entry_points.txt
napari_pymeshlab-0.0.6.dist-info/top_level.txt
napari_pymeshlab-0.0.6.dist-info/RECORD
