Metadata-Version: 2.1
Name: napari-pymeshlab
Version: 0.0.6
Summary: Interfaces between napari and pymeshlab library to allow import, export and construction of surfaces.
Home-page: https://github.com/zacsimile/napari-pymeshlab
Author: Zach Marin, Robert Haase
Author-email: zach.marin@yale.edu
License: MIT
Project-URL: Bug Tracker, https://github.com/zacsimile/napari-pymeshlab/issues
Project-URL: Documentation, https://github.com/zacsimile/napari-pymeshlab#README.md
Project-URL: Source Code, https://github.com/zacsimile/napari-pymeshlab
Project-URL: User Support, https://github.com/zacsimile/napari-pymeshlab/issues
Classifier: Development Status :: 2 - Pre-Alpha
Classifier: Intended Audience :: Developers
Classifier: Framework :: napari
Classifier: Topic :: Software Development :: Testing
Classifier: Programming Language :: Python
Classifier: Programming Language :: Python :: 3
Classifier: Programming Language :: Python :: 3.8
Classifier: Programming Language :: Python :: 3.9
Classifier: Operating System :: OS Independent
Classifier: License :: OSI Approved :: GNU General Public License v3 (GPLv3)
Requires-Python: >=3.8
License-File: LICENSE
Requires-Dist: napari
Requires-Dist: npe2
Requires-Dist: numpy
Requires-Dist: pymeshlab
